{
"type": "FeatureCollection",
"name": "cities",
"crs": { "type": "name", "properties": { "name": "urn:ogc:def:crs:OGC:1.3:CRS84" } },
"features": [
{ "type": "Feature", "properties": { "fid": 1, "name": "Beijing" }, "geometry": { "type": "Point", "coordinates": [ 116.389273937854668, 39.915954821303359 ] } },
{ "type": "Feature", "properties": { "fid": 2, "name": "Nanjing" }, "geometry": { "type": "Point", "coordinates": [ 118.79710897998676, 32.056057297566618 ] } },
{ "type": "Feature", "properties": { "fid": 3, "name": "Hangzhou" }, "geometry": { "type": "Point", "coordinates": [ 120.154298177086645, 30.27264686437255 ] } }
]
}
